{
"type": "FeatureCollection",
                                                                                
"features": [
{ "type": "Feature", "id": 0, "properties": { "NAME": "HBD to the savage @DBeezy12 \ud83d\udc8b\ud83d\udc8b You're wild af, but much love for you" }, "geometry": { "type": "Point", "coordinates": [ -74.988106, 40.760471 ] } }
,
{ "type": "Feature", "id": 1, "properties": { "NAME": "@ChmlBillKelly #LRT, the gift that keeps on giving. #HamOnt" }, "geometry": { "type": "Point", "coordinates": [ -167.51475499999998, 69.19279800000001 ] } }
]
}
